jphelloworld.py
jphellow-0.0.1.dist-info/LICENSE
jphellow-0.0.1.dist-info/METADATA
jphellow-0.0.1.dist-info/WHEEL
jphellow-0.0.1.dist-info/top_level.txt
jphellow-0.0.1.dist-info/RECORD
