Metadata-Version: 2.1
Name: jphellow
Version: 0.0.1
Summary: say hello
Home-page: UNKNOWN
License: UNKNOWN
Platform: UNKNOWN
Classifier: Programming Language :: Python :: 3
Classifier: License :: OSI Approved :: MIT License
Classifier: Operating System :: OS Independent
Requires-Python: >=3.5
Requires-Dist: wheel (>=0.34)
